{
  "id": "LouvreParis",
  "QID_wikidata": "https://www.wikidata.org/wiki/Q1075988",
  "entry_type": "architecture",
  "title": "Palais du Louvre",
  "creator": [],
  "dateCreated": {
    "startYear": "",
    "endYear": "",
    "text": ""
  },
  "typology": null,
  "location": {
    "type": "place",
    "place": {
      "city": "",
      "country": "",
      "coordinates": {
        "latitude": "",
        "longitude": ""
      }
    }
  },
  "related_works": [],
  "bibliography": [],
  "illustrations": [],
  "description": "",
  "commentary": "",
  "history": [
    {
      "date": "2026-01-19T16:01:42.335789",
      "type": "created",
      "author": "Pierre"
    }
  ]
}