{
  "id": "Salle500Florence",
  "QID_wikidata": "https://www.wikidata.org/wiki/Q234364",
  "title": "Salle des Cinq-Cents, Palazzo Vecchio",
  "creator": [],
  "entry_type": "architecture",
  "typology": "",
  "dateCreated": {
    "startYear": "",
    "endYear": "",
    "text": ""
  },
  "location": {
    "type": "place",
    "place": {
      "city": "",
      "country": "",
      "coordinates": {
        "latitude": "",
        "longitude": ""
      }
    }
  },
  "related_works": [],
  "bibliography": [],
  "illustrations": [],
  "description": "",
  "commentary": "",
  "history": [
    {
      "date": "2026-01-20T11:47:35.422574",
      "type": "created",
      "author": "Pierre"
    }
  ]
}